keklib/__init__.py
keklib/ast_visitor.py
keklib/fib_numbers.py
keklib/main.py
keklib-0.5.dist-info/METADATA
keklib-0.5.dist-info/WHEEL
keklib-0.5.dist-info/top_level.txt
keklib-0.5.dist-info/RECORD
