Metadata-Version: 2.1
Name: keklib
Version: 0.5
Summary: hw_01
License: UNKNOWN
Platform: UNKNOWN
Requires-Dist: networkx (==2.6.3)
